{
  "address": [
    {
      "cep": "69086771",
      "rua": "Rua do Igarapé",
      "numero": "17",
      "bairro": "Zumbi I",
      "cidade": "Manaus",
      "estado": "Amazonas",
      "complemento": "Perto do T5",
      "ponto_referencia": "",
      "nome": "Minha Casa",
      "id": 3
    },
    {
      "cep": "69086772",
      "rua": "Rua da Ressurreição",
      "numero": "179",
      "bairro": "Grande Vitoria",
      "cidade": "Manaus",
      "estado": "AM",
      "complemento": "",
      "ponto_referencia": "4 DIP",
      "nome": "Casa Oz",
      "id": 4
    },
    {
      "cep": "69085180",
      "rua": "Rua Barreirinha",
      "numero": "628",
      "bairro": "São José Operário",
      "cidade": "Manaus",
      "estado": "AM",
      "complemento": "Em frente ao merca. Rosa de Saron",
      "ponto_referencia": "Baratão da Carne",
      "nome": "Casa Big",
      "id": 5
    }
  ]
}